[
  {
    "question": "Which city will host the 2026 UN Climate Change Conference (COP31)?",
    "options": ["Paris", "Antalya", "Nairobi", "New York"],
    "answer": "Antalya"
  },
  {
    "question": "Where will GLF Africa 2026: Stewarding Our Rangelands be held?",
    "options": ["Cape Town", "Nairobi", "Lagos", "Cairo"],
    "answer": "Nairobi"
  },
  {
    "question": "Which ocean currently shows rising temperatures that may help prevent global droughts?",
    "options": ["Atlantic", "Pacific", "Indian", "Arctic"],
    "answer": "Pacific"
  },
  {
    "question": "Which forests are releasing massive carbon emissions due to wildfires in 2026?",
    "options": ["Amazon Rainforest", "Boreal Forests", "Congo Basin", "Taiga"],
    "answer": "Boreal Forests"
  },
  {
    "question": "K’gari, the world’s largest sand island, is located in which country?",
    "options": ["Australia", "New Zealand", "South Africa", "Madagascar"],
    "answer": "Australia"
  },
  {
    "question": "Which continent has the largest population in 2026?",
    "options": ["Africa", "Asia", "Europe", "South America"],
    "answer": "Asia"
  },
  {
    "question": "Which desert remains the largest in the world?",
    "options": ["Sahara", "Gobi", "Antarctic Desert", "Kalahari"],
    "answer": "Antarctic Desert"
  },
  {
    "question": "Which country is experiencing major rangeland discussions in 2026 due to climate change?",
    "options": ["Kenya", "Brazil", "India", "Canada"],
    "answer": "Kenya"
  },
  {
    "question": "Which mountain continues to be the highest in the world?",
    "options": ["Mount Everest", "K2", "Denali", "Kangchenjunga"],
    "answer": "Mount Everest"
  },
  {
    "question": "Which ocean is the largest by area?",
    "options": ["Atlantic", "Indian", "Pacific", "Arctic"],
    "answer": "Pacific"
  }
]